kmm/__init__.py
kmm/car_direction.py
kmm/functional_base.py
kmm/header/__init__.py
kmm/header/car_direction.py
kmm/header/header.py
kmm/header/position_sync.py
kmm/position_adjustment.py
kmm/positions/__init__.py
kmm/positions/geodetic.py
kmm/positions/positions.py
kmm/positions/read_kmm.py
kmm/positions/read_kmm2.py
kmm/positions/sync_frame_index.py
kmm-0.1.7.dist-info/LICENSE
kmm-0.1.7.dist-info/METADATA
kmm-0.1.7.dist-info/WHEEL
kmm-0.1.7.dist-info/RECORD
