Metadata-Version: 2.1
Name: kmm
Version: 0.1.7
Summary: Minimalistic library for reading files in the kmm/kmm2 file format
License: Apache 2.0
Author: NextML AB
Requires-Python: >=3.8,<3.11
Classifier: License :: Other/Proprietary License
Classifier: Programming Language :: Python :: 3
Classifier: Programming Language :: Python :: 3.8
Classifier: Programming Language :: Python :: 3.9
Classifier: Programming Language :: Python :: 3.10
Requires-Dist: numpy (>=1.21.2,<2.0.0)
Requires-Dist: pandas (>=1.3.2,<2.0.0)
Requires-Dist: pydantic (>=2.0.0,<3.0.0)
Requires-Dist: sweref99 (==0.2)
